---
layout: post
title:  "初识 JVM"
date:   2024-01-10 00:00:00 +0800
categories: 杂项
tags: java jvm
comments: true
mathjax: true
copyrights: 原创
draft: true
---

Java 如今已经成为了世界上最流行的编程语言之一，而 Java 的虚拟机 JVM 也是 Java 语言的核心。JVM 是 Java 的运行环境，它负责将 Java 代码编译成机器码并运行。本文将初步介绍 JVM 的基本概念。

## 从源代码到机器码

编程语言根据如何执行，可以分为两类：

- **编译型语言**

  源代码在运行前先编译成机器码，然后再运行机器码。例如 C、C++。编译型语言的代码在编写时，会使用到和硬件、操作系统相关的特性，编译后的机器码通常只能在特定的硬件和操作系统上运行。
  
  尽管交叉编译可以让一个程序编译为多个平台的可执行文件，但编译型语言编写的程序也往往是不同的。例如对于 C 语言，我们在 Windows 上会使用 `windows.h` 来调用 Windows API，而在 Linux 上则会使用 `unistd.h` 来调用 Linux API。

- **解释型语言**

  源代码在运行时逐行解释执行。例如 Python、JavaScript。解释型语言的代码在编写时，通常不会使用到和硬件、操作系统相关的特性，通常所有平台使用的代码是一模一样的。

Java 是一种特殊的编译型语言，它的编译运行分为两步：

1. 由源代码编译为字节码
2. JVM 翻译字节码并执行，有时也会将部分字节码编译为机器码

### 前端编译器

源代码到字节码这步由前端编译器完成。我们通常使用的 `javac` 命令就是一个前端编译器，它将 Java 源代码编译为字节码文件（`.class` 文件）。

我们新建一个 `Hello.java` 文件：

```java
public class Hello {
    public static void main(String[] args) {
        System.out.println("Hello, world!");
    }
}
```

然后使用 `javac` 编译：

```shell
javac Hello.java
```

编译后会生成一个 `Hello.class` 文件，这个文件就是字节码文件。我们使用任意二进制编辑器打开这个文件，可以看到：

```plaintext
CA FE BA BE 00 00 00 41 00 1D 0A 00 02 00 03 07
00 04 0C 00 05 00 06 01 00 10 6A 61 76 61 2F 6C
61 6E 67 2F 4F 62 6A 65 63 74 01 00 06 3C 69 6E
69 74 3E 01 00 03 28 29 56 09 00 08 00 09 07 00
0A 0C 00 0B 00 0C 01 00 10 6A 61 76 61 2F 6C 61
6E 67 2F 53 79 73 74 65 6D 01 00 03 6F 75 74 01
00 15 4C 6A 61 76 61 2F 69 6F 2F 50 72 69 6E 74
53 74 72 65 61 6D 3B 08 00 0E 01 00 0D 48 65 6C
6C 6F 2C 20 77 6F 72 6C 64 21 0A 00 10 00 11 07
00 12 0C 00 13 00 14 01 00 13 6A 61 76 61 2F 69
6F 2F 50 72 69 6E 74 53 74 72 65 61 6D 01 00 07
70 72 69 6E 74 6C 6E 01 00 15 28 4C 6A 61 76 61
2F 6C 61 6E 67 2F 53 74 72 69 6E 67 3B 29 56 07
00 16 01 00 05 48 65 6C 6C 6F 01 00 04 43 6F 64
65 01 00 0F 4C 69 6E 65 4E 75 6D 62 65 72 54 61
62 6C 65 01 00 04 6D 61 69 6E 01 00 16 28 5B 4C
6A 61 76 61 2F 6C 61 6E 67 2F 53 74 72 69 6E 67
3B 29 56 01 00 0A 53 6F 75 72 63 65 46 69 6C 65
01 00 0A 48 65 6C 6C 6F 2E 6A 61 76 61 00 21 00
15 00 02 00 00 00 00 00 02 00 01 00 05 00 06 00
01 00 17 00 00 00 1D 00 01 00 01 00 00 00 05 2A
B7 00 01 B1 00 00 00 01 00 18 00 00 00 06 00 01
00 00 00 01 00 09 00 19 00 1A 00 01 00 17 00 00
00 25 00 02 00 01 00 00 00 09 B2 00 07 12 0D B6
00 0F B1 00 00 00 01 00 18 00 00 00 0A 00 02 00
00 00 03 00 08 00 04 00 01 00 1B 00 00 00 02 00
1C
```

这个字节码文件的格式遵循了 [Java Virtual Machine Specification](https://docs.oracle.com/javase/specs/jvms/se21/html/jvms-4.html) 的规范。接下来我们按顺序解读这个字节码文件：

<details>
<summary>点击展开具体的分析过程</summary>
<div markdown="1">

- `CA FE BA BE`

  前 4 个字节为 Magic Number，标识这是一个 Java 字节码文件

- `00 00 00 41`

  接下来 4 个字节为版本号，其中 `00 00` 为次版本号，`00 41` 为主版本号。主版本号的数字是顺序排列的，例如 JDK 1.8 是 `0x34`、JDK 17 是 `0x3D`、JDK 21 是 `0x41`。由此可知，这个字节码文件是 Java 21。

- `00 1D`

  接下来 2 个字节为常量池大小，这里有 $$29-1=28$$ 个常量。

  规范规定，常量共有 17 种类型，每种都有一个 1 字节的 tag 标识。具体对应关系可以参考 [Java Virtual Machine Specification](https://docs.oracle.com/javase/specs/jvms/se21/html/jvms-4.html) 的表 4.4-A。每种常量的结构也不同，我们接下来会通过例子解读。

  - `0A 00 02 00 03`（第 1 个常量）

    首先，`0A` 是这个常量的 tag，表示这是一个 `CONSTANT_Methodref_info` 类型的常量。查阅规范的第 4.4.2 节，我们可以知道这个常量的结构如下：

    ```c
    CONSTANT_Methodref_info {
        u1 tag;
        u2 class_index;
        u2 name_and_type_index;
    }
    ```

    因此，`00 02` 是 `class_index`，即该常量的类型，其指向常量池中的第 2 个常量；`00 03` 是 `name_and_type_index`，即该常量的名字和类型，其指向常量池中的第 3 个常量。

    通过后文我们可以知道，这个常量表示一个方法引用，其类名是 `java/lang/Object`，方法名是 `<init>`，方法类型是 `()V`。即调用了 `java/lang/Object` 类的无参构造函数。

    我们继续查看常量池中的第 2 个常量。

  - `07 00 04`（第 2 个常量）
  
    这个常量的 tag 是 `CONSTANT_Class_info`，表示这是一个类名。查阅规范的第 4.4.1 节，我们可以知道这个常量的结构如下：

    ```c
    CONSTANT_Class_info {
        u1 tag;
        u2 name_index;
    }
    ```

    因此，`00 04` 是 `name_index`，即类的名字，其指向常量池中的第 4 个常量。

    根据后文我们可以知道，这个类名是 `java/lang/Object`。

  - `0C 00 05 00 06`（第 3 个常量）

    这个常量的 tag 是 `CONSTANT_NameAndType_info`，表示这是一个名字和类型。查阅规范的第 4.4.6 节，我们可以知道这个常量的结构如下：

    ```c
    CONSTANT_NameAndType_info {
        u1 tag;
        u2 name_index;
        u2 descriptor_index;
    }
    ```

    因此，`00 05` 是 `name_index`，即名字，其指向常量池中的第 5 个常量；`00 06` 是 `descriptor_index`，即类型，其指向常量池中的第 6 个常量。

    根据后文我们可以知道，这个名字是 `<init>`，这个类型是 `()V`。即调用了一个无参构造函数。

    怎么一环套一环，跟递归似的！

  - `01 00 10 6A 61 76 61 2F 6C 61 6E 67 2F 4F 62 6A 65 63 74`（第 4 个常量）

    这个常量的 tag 是 `CONSTANT_Utf8_info`，表示这是一个 UTF-8 编码的字符串。查阅规范的第 4.4.7 节，我们可以知道这个常量的结构如下：

    ```c
    CONSTANT_Utf8_info {
        u1 tag;
        u2 length;
        u1 bytes[length];
    }
    ```

    因此，`00 10` 是 `length`，即字符串的长度，其长度为 16；因此，我们往后数 16 个字节，内容为 `6A 61 76 61 2F 6C 61 6E 67 2F 4F 62 6A 65 63 74`。这一段就是 `bytes`，即字符串的内容，其内容为 `java/lang/Object`。

  - `01 00 06 3C 69 6E 69 74 3E`（第 5 个常量）

    这个常量的 tag 是 `CONSTANT_Utf8_info`，内容为 `<init>`。

    `<init>` 是 Java 中的构造函数的名字。

  - `01 00 03 28 29 56`（第 6 个常量）

    这个常量的 tag 是 `CONSTANT_Utf8_info`，内容为 `28 29 56` `()V`。

    `()` 表示这个方法没有参数，`V` 表示这个方法没有返回值。

  - `09 00 08 00 09`（第 7 个常量）

    这个常量的 tag 是 `CONSTANT_Fieldref_info`，表示这是一个字段引用。查阅规范的第 4.4.2 节，我们可以知道这个常量的结构如下：

    ```c
    CONSTANT_Fieldref_info {
        u1 tag;
        u2 class_index;
        u2 name_and_type_index;
    }
    ```

    因此，`00 08` 是 `class_index`，即该常量的类型，其指向常量池中的第 8 个常量；`00 09` 是 `name_and_type_index`，即该常量的名字和类型，其指向常量池中的第 9 个常量。

    通过后文我们可以知道，这个常量表示一个字段引用，其类名是 `java/lang/System`，方法名是 `out`，方法返回值类型是 `Ljava/io/PrintStream;`。因此，这个常量表示了一个 `java.lang.System.out` 的引用。

  - `07 00 0A`（第 8 个常量）

    这个常量的 tag 是 `CONSTANT_Class_info`，其指向常量池中的第 10 个常量。

    根据后文我们可以知道，这个类名是 `java/lang/System`。

  - `0C 00 0B 00 0C`（第 9 个常量）
  
    这个常量的 tag 是 `CONSTANT_NameAndType_info`，其指向常量池中的第 12 个常量。

    根据后文我们可以知道，这个名字是 `out`，这个类型是 `Ljava/io/PrintStream;`。即方法名为 `out`，方法返回类型类型为 `PrintStream`。

  - `01 00 10 6A 61 76 61 2F 6C 61 6E 67 2F 53 79 73 74 65 6D`（第 10 个常量）

    这个常量的 tag 是 `CONSTANT_Utf8_info`，其内容为 `java/lang/System`。

  - `01 00 03 6F 75 74`（第 11 个常量）
  
    这个常量的 tag 是 `CONSTANT_Utf8_info`，内容为 `out`。

  - `01 00 15 4C 6A 61 76 61 2F 69 6F 2F 50 72 69 6E 74 53 74 72 65 61 6D 3B`（第 12 个常量）

    这个常量的 tag 是 `CONSTANT_Utf8_info`，其内容为 `Ljava/io/PrintStream;`。

  - `08 00 0E`（第 13 个常量）

    这个常量的 tag 是 `CONSTANT_String_info`，表示这是一个字符串。查阅规范的第 4.4.3 节，我们可以知道这个常量的结构如下：

    ```c
    CONSTANT_String_info {
        u1 tag;
        u2 string_index;
    }
    ```

    因此，`00 0E` 是 `string_index`，即字符串的索引，其指向常量池中的第 14 个常量。

    根据后文我们可以知道，这个常量表示了一个字符串，其内容为 `Hello, world!`。

  - `01 00 0D 48 65 6C 6C 6F 2C 20 77 6F 72 6C 64 21`（第 14 个常量）

    这个常量的 tag 是 `CONSTANT_Utf8_info`，内容为 `Hello, world!`。

  - `0A 00 10 00 11`（第 15 个常量）

    这个常量的 tag 是 `CONSTANT_Methodref_info`。`class_index` 指向常量池中的第 16 个常量；`name_and_type_index` 指向常量池中的第 17 个常量。

    通过后文我们可以知道，这个常量表示一个方法引用，其类名是 `java/io/PrintStream`，方法名是 `println`，方法类型是 `(Ljava/lang/String;)V`。即调用了 `java.io.PrintStream.println` 方法。

  - `07 00 12`（第 16 个常量）

    这个常量的 tag 是 `CONSTANT_Class_info`，其指向常量池中的第 18 个常量。

    根据后文我们可以知道，这个类名是 `java/io/PrintStream`。

  - `0C 00 13 00 14`（第 17 个常量）

    这个常量的 tag 是 `CONSTANT_NameAndType_info`。`name_index` 指向常量池中的第 19 个常量；`descriptor_index` 指向常量池中的第 20 个常量。

    根据后文我们可以知道，这个名字是 `println`，这个类型是 `(Ljava/lang/String;)V`。即方法名为 `println`，方法返回类型为 `void`。

  - `01 00 13 6A 61 76 61 2F 69 6F 2F 50 72 69 6E 74 53 74 72 65 61 6D`（第 18 个常量）

    这个常量的 tag 是 `CONSTANT_Utf8_info`，其内容为 `java/io/PrintStream`。

  - `01 00 07 70 72 69 6E 74 6C 6E`（第 19 个常量）

    这个常量的 tag 是 `CONSTANT_Utf8_info`，内容为 `println`。

  - `01 00 15 28 4C 6A 61 76 61 2F 6C 61 6E 67 2F 53 74 72 69 6E 67 3B 29 56`（第 20 个常量）

    这个常量的 tag 是 `CONSTANT_Utf8_info`，其内容为 `(Ljava/lang/String;)V`。

  - `07 00 16`（第 21 个常量）

    这个常量的 tag 是 `CONSTANT_Class_info`，其指向常量池中的第 22 个常量。

    根据后文我们可以知道，这个类名是 `Hello`。

  - `01 00 05 48 65 6C 6C 6F`（第 22 个常量）

    这个常量的 tag 是 `CONSTANT_Utf8_info`，内容为 `Hello`。

  - `01 00 04 43 6F 64 65`（第 23 个常量）

    这个常量的 tag 是 `CONSTANT_Utf8_info`，内容为 `Code`。

  - `01 00 0F 4C 69 6E 65 4E 75 6D 62 65 72 54 61 62 6C 65`（第 24 个常量）

    这个常量的 tag 是 `CONSTANT_Utf8_info`，内容为 `4C 69 6E 65 4E 75 6D 62 65 72 54 61 62 6C 65`，即 `LineNumberTable`。

  - `01 00 04 6D 61 69 6E`（第 25 个常量）

    这个常量的 tag 是 `CONSTANT_Utf8_info`，内容为 `main`。

  - `01 00 16 28 5B 4C 6A 61 76 61 2F 6C 61 6E 67 2F 53 74 72 69 6E 67 3B 29 56`（第 26 个常量）

    这个常量的 tag 是 `CONSTANT_Utf8_info`，内容为 `([Ljava/lang/String;)V`。

  - `01 00 0A 53 6F 75 72 63 65 46 69 6C 65`（第 27 个常量）
  
    这个常量的 tag 是 `CONSTANT_Utf8_info`，内容为 `53 6F 75 72 63 65 46 69 6C 65`，即 `SourceFile`。

  - `01 00 0A 48 65 6C 6C 6F 2E 6A 61 76 61`（第 28 个常量）

    这个常量的 tag 是 `CONSTANT_Utf8_info`，内容为 `Hello.java`。

  现在我们回过去看，整个常量池的结构就清晰了：

  ```plaintext
  #1 = java/lang/Object.<init>:()V
  #7 = java/lang/System.out:Ljava/io/PrintStream;
  #13 = Hello, world!
  #15 = java/io/PrintStream.println:(Ljava/lang/String;)V
  #21 = Hello
  #23 = Code
  #24 = LineNumberTable
  #25 = main
  #26 = ([Ljava/lang/String;)V
  #27 = SourceFile
  #28 = Hello.java
  ```

  我们可以使用 `javap` 命令来查看这个字节码文件的内容：

  ```shell
  javap -v Hello.class
  ```

  得到的结果是一样的。

- `00 21`

  接下来 2 个字节为访问标志，它的取值在规范的表 4.1-B 中定义。这里的 `00 21` 由 `0x0001` 和 `0x0020` 相加得到，分别表示 `ACC_PUBLIC` 和 `ACC_SUPER`。

  JDK 1.2 之后的版本中 `ACC_SUPER` 一定会被设置，因此我们认为这个类是个基本的 public 类。

- `00 15`

  接下来 2 个字节为类名索引，其指向常量池中的第 21 个常量。

  根据常量池我们可以知道，这个类名是 `Hello`。

- `00 02`

  接下来 2 个字节为父类名索引，其指向常量池中的第 2 个常量。

  根据常量池我们可以知道，这个父类名是 `java/lang/Object`。说明这个类没有手动继承任何类，因此默认继承了 `java.lang.Object`。

- `00 00`

  接下来 2 个字节为接口数量，这里为 0。因此，接下来也不会由接口表。

- `00 00`

  接下来 2 个字节为字段表数量，这里为 0。因此，接下来也不会有字段表。

- `00 02`

  接下来 2 个字节为方法表数量，这里为 2。说明这个类有两个方法。

  - `00 01 00 05 00 06 00 01 00 17 00 00 00 1D 00 01 00 01 00 00 00 05 2A B7 00 01 B1 00 00 00 01 00 18 00 00 00 06 00 01 00 00 00 01`

    - 前两个字节 `00 01` 为访问标志，查表可知为 `ACC_PUBLIC`；

    - 接下来 2 个字节 `00 05` 为方法名索引，其指向常量池中的第 5 个常量，即 `<init>`；

    - 接下来 2 个字节 `00 06` 为描述符索引，其指向常量池中的第 6 个常量，即 `()V`；

    - 接下来 2 个字节 `00 01` 为属性表数量，这里为 1，说明这个方法有一个属性；

      - 该属性内容为 `00 17 00 00 00 1D 00 01 00 01 00 00 00 05 2A B7 00 01 B1 00 00 00 01`，其中：

        - 前 2 个字节 `00 17` 为属性名索引，其指向常量池中的第 23 个常量，即 `Code`；

        - 接下来 4 个字节 `00 00 00 1D` 为属性长度，这里为 29；

        - 接下来 2 个字节 `00 01` 为最大栈深度，这里为 1；

        - 接下来 2 个字节 `00 01` 为局部变量表大小，这里为 1；

        - 接下来 4 个字节 `00 00 00 05` 为代码长度，这里为 5；

          - 接下来 5 个字节 `2A B7 00 01 B1` 为代码，其内容为：

            - `2A` 表示 `aload_0`，即将第 0 个局部变量（即 `this`）压入栈顶；

            - `B7 00 01` 表示 `invokespecial #1`，即调用常量池中的第 1 个方法；

            - `B1` 表示 `return`，即返回。

        - 接下来 2 个字节 `00 00` 为异常表大小，这里为 0；

        - 接下来 2 个字节 `00 01` 为属性表大小，这里为 1；

          - 该属性内容为 `00 18 00 00 00 06 00 01 00 00 00 01`，其中：

            - 前 2 个字节 `00 18` 为属性名索引，其指向常量池中的第 24 个常量，即 `LineNumberTable`；

            - 接下来 4 个字节 `00 00 00 06` 为属性长度，这里为 6；

            - 接下来 2 个字节 `00 01` 为行号表大小，这里为 1；

              - 该行号表内容为 `00 00 00 01`，其中：

                - 前 2 个字节 `00 00` 为开始 PC，这里为 0；

                - 接下来 2 个字节 `00 01` 为行号，这里为 1。

    这个方法的内容是调用 `java/lang/Object` 的无参构造函数。

  - `00 09 00 19 00 1A 00 01 00 17 00 00 00 25 00 02 00 01 00 00 00 09 B2 00 07 12 0D B6 00 0F B1 00 00 00 01 00 18 00 00 00 0A 00 02 00 00 00 03 00 08 00 04`

    - 前两个字节 `00 09` 为访问标志，查表可知为 `public static`；

    - 接下来 2 个字节 `00 19` 为方法名索引，其指向常量池中的第 25 个常量，即 `main`；

    - 接下来 2 个字节 `00 1A` 为描述符索引，其指向常量池中的第 26 个常量，即 `([Ljava/lang/String;)V`；

    - 接下来 2 个字节 `00 01` 为属性表数量，这里为 1，说明这个方法有一个属性；

      - 该属性内容为 `00 17 00 00 00 25 00 02 00 01 00 00 00 09 B2 00 07 12 0D B6 00 0F B1 00 00 00 01 00 18 00 00 00 0A 00 02 00 00 00 03 00 08 00 04`，其中：

        - 前 2 个字节 `00 17` 为属性名索引，其指向常量池中的第 23 个常量，即 `Code`；

        - 接下来 4 个字节 `00 00 00 25` 为属性长度，这里为 37；

        - 接下来 2 个字节 `00 02` 为最大栈深度，这里为 2；

        - 接下来 2 个字节 `00 01` 为局部变量表大小，这里为 1；

        - 接下来 4 个字节 `00 00 00 09` 为代码长度，这里为 9；

          - 接下来 9 个字节 `B2 00 07 12 0D B6 00 0F B1` 为代码，其内容为：

            - `B2 00 07` 表示 `getstatic #7`，即获取 `java/lang/System.out:Ljava/io/PrintStream;`；

            - `12 0D` 表示 `ldc #13`，即加载常量池中的第 13 个常量，即 `Hello, world!`；

            - `B6 00 0F` 表示 `invokevirtual #15`，即调用 `java/io/PrintStream.println:(Ljava/lang/String;)V`；

            - `B1` 表示 `return`，即返回。

        - 接下来 2 个字节 `00 00` 为异常表大小，这里为 0；

        - 接下来 2 个字节 `00 01` 为属性表大小，这里为 1；

          - 该属性内容为 `00 18 00 00 00 0A 00 02 00 00 00 03 00 08 00 04`，其中：

            - 前 2 个字节 `00 18` 为属性名索引，其指向常量池中的第 24 个常量，即 `LineNumberTable`；

            - 接下来 4 个字节 `00 00 00 0A` 为属性长度，这里为 10；

            - 接下来 2 个字节 `00 02` 为行号表大小，这里为 2；

              - 行号表第一行为 `00 00 00 03`，即开始 PC 为 0，行号为 3；

              - 行号表第二行为 `00 08 00 04`，即开始 PC 为 8，行号为 4。

    这个方法的内容是调用 `java.lang.System.out.println` 方法。

- `00 01`

  接下来 2 个字节为类的属性表数量，这里为 1。说明这个类有一个属性。

  - `00 1B 00 00 00 02 00 1C`

    - 前 2 个字节 `00 1B` 为属性名索引，其指向常量池中的第 27 个常量，即 `SourceFile`；

    - 接下来 4 个字节 `00 00 00 02` 为属性长度，这里为 2；

    - 接下来 2 个字节 `00 1C` 为源文件名索引，其指向常量池中的第 28 个常量，即 `Hello.java`。

    这个属性表示这个类的源文件名是 `Hello.java`。

</div>
</details>

终于分析完了！

我们可以对比一下 `javap` 的输出：

```plaintext
public class Hello
  minor version: 0
  major version: 65
  flags: (0x0021) ACC_PUBLIC, ACC_SUPER
  this_class: #21                         // Hello
  super_class: #2                         // java/lang/Object
  interfaces: 0, fields: 0, methods: 2, attributes: 1
Constant pool:
   #1 = Methodref          #2.#3          // java/lang/Object."<init>":()V
   #2 = Class              #4             // java/lang/Object
   #3 = NameAndType        #5:#6          // "<init>":()V
   #4 = Utf8               java/lang/Object
   #5 = Utf8               <init>
   #6 = Utf8               ()V
   #7 = Fieldref           #8.#9          // java/lang/System.out:Ljava/io/PrintStream;
   #8 = Class              #10            // java/lang/System
   #9 = NameAndType        #11:#12        // out:Ljava/io/PrintStream;
  #10 = Utf8               java/lang/System
  #11 = Utf8               out
  #12 = Utf8               Ljava/io/PrintStream;
  #13 = String             #14            // Hello, world!
  #14 = Utf8               Hello, world!
  #15 = Methodref          #16.#17        // java/io/PrintStream.println:(Ljava/lang/String;)V
  #16 = Class              #18            // java/io/PrintStream
  #17 = NameAndType        #19:#20        // println:(Ljava/lang/String;)V
  #18 = Utf8               java/io/PrintStream
  #19 = Utf8               println
  #20 = Utf8               (Ljava/lang/String;)V
  #21 = Class              #22            // Hello
  #22 = Utf8               Hello
  #23 = Utf8               Code
  #24 = Utf8               LineNumberTable
  #25 = Utf8               main
  #26 = Utf8               ([Ljava/lang/String;)V
  #27 = Utf8               SourceFile
  #28 = Utf8               Hello.java
{
  public Hello();
    descriptor: ()V
    flags: (0x0001) ACC_PUBLIC
    Code:
      stack=1, locals=1, args_size=1
         0: aload_0
         1: invokespecial #1                  // Method java/lang/Object."<init>":()V
         4: return
      LineNumberTable:
        line 1: 0

  public static void main(java.lang.String[]);
    descriptor: ([Ljava/lang/String;)V
    flags: (0x0009) ACC_PUBLIC, ACC_STATIC
    Code:
      stack=2, locals=1, args_size=1
         0: getstatic     #7                  // Field java/lang/System.out:Ljava/io/PrintStream;
         3: ldc           #13                 // String Hello, world!
         5: invokevirtual #15                 // Method java/io/PrintStream.println:(Ljava/lang/String;)V
         8: return
      LineNumberTable:
        line 3: 0
        line 4: 8
}
SourceFile: "Hello.java"
```

可以说，跟我们解读出来的不能说是一模一样，只能说是毫无区别的。

### JIT 编译器

JVM 拿到字节码文件后，会解释执行字节码。这种方法启动速度很快，但是执行速度很慢。因此，JVM 会采取混合的方式，在运行时将一部分字节码编译成本地机器码，以提高程序的执行效率。这个过程就是 JIT 编译器。

JIT 编译器（Just-In-Time Compiler）是 Java 虚拟机的一部分，它的作用是将 Java 字节码编译成本地机器码，以提高程序的执行效率。

HopSpot VM 内置了两个 JIT 编译器：C1 编译器和 C2 编译器。

- C1 编译器：也叫做 Client 编译器，它是一个轻量级的编译器，主要用于对代码进行快速编译，以提高程序的启动速度。C1 编译器的编译速度快，但是生成的机器码质量一般。它适合对代码进行快速编译，以提高程序的启动速度，常常用于客户端应用程序。

- C2 编译器：也叫做 Server 编译器，它是一个重量级的编译器，主要用于对代码进行优化编译，以提高程序的执行速度。C2 编译器的编译速度慢，但是生成的机器码质量高。它适合对代码进行优化编译，以提高程序的执行速度，常常用于服务器端应用程序。

我们在使用 `java` 命令时，对 JVM 的执行模式可以有如下几种选择：

- 默认模式为混合模式，即在程序运行过程中，JVM 会根据程序的运行情况，动态地选择 C1 编译器和 C2 编译器
- `-client` 参数表示使用 C1 编译器
- `-server` 参数表示使用 C2 编译器
- `-Xint` 参数表示关闭 JIT 编译器，即完全采用解释执行的方式
- `-Xcomp` 参数表示关闭解释执行，即完全采用编译执行的方式

使用 `java -version` 就可以看到当前 JVM 的执行模式。

### AOT 编译器

AOT 编译器（Ahead-Of-Time Compiler）是一种在程序运行之前将 Java 字节码编译成本地机器码的编译器。AOT 编译器的优点是可以提高程序的启动速度，缺点是会增加程序的体积。

AOT 跟随 [JEP 295](https://openjdk.org/jeps/295) 在 Java 9 中引入，但在 Java 17 时，已经被 [JEP 410](https://openjdk.org/jeps/410) 删除。

## 类加载器

类加载器（ClassLoader）是 Java 虚拟机的一个重要组成部分，它的作用是将类的字节码文件加载到 Java 虚拟机中，以便程序能够运行。

这个过程分为七个阶段：加载、验证、准备、解析、初始化、使用和卸载。

### 加载

加载（Loading）是类加载器的第一个阶段，主要作用是将类的字节码文件加载到 Java 虚拟机中，并将其转换成 Java 虚拟机可以执行的类。

### 验证

验证（Verification）是类加载器的第二个阶段，主要会做下面几件事情：

- 文件格式验证

- 元数据验证

- 字节码验证

- 符号引用验证

### 准备

准备（Preparation）是类加载器的第三个阶段，主要会按照代码语句的顺序，做下面几件事情：

- 为类的静态变量（`static`）分配内存

  - 为变量赋予默认值，即零值

  - 为常量（`final`）赋予用户指定的值

- 执行类的静态代码块（`static {}`）

### 解析

解析（Resolution）是类加载器的第四个阶段，JVM 会将类或接口、字段、类方法、接口方法、方法类型、方法句柄和调用点限定符的符号引用解析为直接引用。

### 初始化

初始化（Initialization）是类加载器的第五个阶段，JVM 会按照语句的顺序执行类的初始化方法：

- `new`、`getstatic`、`putstatic` 或 `invokestatic` 字节码指令会触发对应类的初始化。这四条字节码常常由以下代码产生：

  - 使用 `new` 关键字创建类的实例

  - 读取或设置一个类的静态字段（被 `final` 修饰的静态字段和在常量池中的静态字段除外）

  - 调用一个类的静态方法

- 使用 `java.lang.reflect` 包的 `Method` 对象的 `invoke` 方法

- 初始化一个类的子类会触发父类的初始化

- 虚拟机启动时，会初始化 `main` 方法所在的类

- 当使用 `JDK 1.7` 的 `java.lang.invoke.MethodHandle` 实例的 `invoke` 方法句柄时，初始化该 `MethodHandle` 指向的类

- 当一个接口中定义了 `default` 方法时，如果有这个接口的实现类被初始化，那么这个接口也会被初始化

### 使用

使用（Using）是类加载器的第六个阶段，主要是程序运行时，Java 虚拟机会执行程序的代码。

JVM 会从 `main` 方法开始执行，然后按照代码的顺序执行。

### 卸载

卸载（Unloading）是类加载器的第七个阶段，主要是当类加载器不再需要加载某个类时，Java 会卸载这个类。

我们接下来看一个例子：

```java
public class InitializationDemo {

    public static void main(String[] args) {
        staticFunction();
    }

    int a = 1;
    static int b = 2;
    static final int c = 3;

    static InitializationDemo id = new InitializationDemo();

    static final Son son = new Son();

    static {
        System.out.println("主类的静态代码块");
    }

    public InitializationDemo() {
        System.out.println("主类的构造方法");
        System.out.println("a=" + a + " b=" + b + " c=" + c + " d=" + d + " e=" + e + " f=" + f);
    }

    public static void staticFunction() {
        System.out.println("主类的静态方法");
    }

    {
        System.out.println("主类的普通代码块");
    }

    int d = 4;
    static int e = 5;
    static final int f = 6;
}

class Son extends Father {

    static {
        System.out.println("子类的静态代码块");
    }

    public Son() {
        System.out.println("我是子类");
    }
}

class Father {

    static {
        System.out.println("父类的静态代码块");
    }

    public Father() {
        System.out.println("我是父类");
    }
}
```

输出为：

```plaintext
主类的普通代码块
主类的构造方法
a=1 b=2 c=3 d=4 e=0 f=6
父类的静态代码块
子类的静态代码块
我是父类
我是子类
主类的静态代码块
主类的静态方法
```

我们来分析一下这个程序的输出：

<details>
<summary>点击展开分析</summary>
<div markdown="1">

- 首先 JVM 会初始化 `main` 方法所在的类 `InitializationDemo` 类，首先执行 `static`：

  ```java
  static int b = 2;
  static final int c = 3;
  static InitializationDemo id = new InitializationDemo();
  static Son son = new Son();
  static {
      System.out.println("主类的静态代码块");
  }
  static int e = 5;
  static final int f = 6;
  ```

  - 为所有静态变量（`b`、`c`、`id`、`son`、`e`、`f`）分配内存，其中：

    - `b` 赋予默认值 `0`
    - `c` 为 `final`，赋予 `3`
    - `id` 赋予默认值 `null`
    - `son` 虽然为 `final`，但此刻无法执行 `new`，赋予默认值 `null`
    - `e` 赋予默认值 `0`
    - `f` 为 `final`，赋予 `6`

  - 静态变量依次初始化：

    - `b` 赋予 `2`
    - `id` 赋予 `new InitializationDemo()`，出发了 `InitializationDemo` 的构造方法

- `InitializationDemo` 实例化时：

  - 首先执行普通代码块和普通变量初始化：

    ```java
    int a = 1;
    {
        System.out.println("主类的普通代码块");
    }
    int d = 4;
    ```

    - `a` 赋予 `1`
    - 输出 `主类的普通代码块`
    - `d` 赋予 `4`

  - 然后执行构造方法：

    ```java
    public InitializationDemo() {
        System.out.println("主类的构造方法");
        System.out.println("a=" + a + " b=" + b + " c=" + c + " d=" + d + " e=" + e + " f=" + f);
    }
    ```

    - 输出 `主类的构造方法`
    - 输出 `a=1 b=2 c=3 d=4 e=0 f=6`

- 然后回到 `static`，将刚刚实例化后的 `InitializationDemo` 类赋予 `id`

- 继续执行 `static` 部分，`son` 也有 `new`，触发了 `Son` 类的初始化。

- `Son` 类初始化时，由于继承了 `Father` 类，因此 `Father` 类也会被初始化。

  - 首先执行 `Father` 类的 `static`：

    ```java
    static {
        System.out.println("父类的静态代码块");
    }
    ```

    - 输出 `父类的静态代码块`

  - 然后执行 `Son` 类的 `static`：

    ```java
    static {
        System.out.println("子类的静态代码块");
    }
    ```

    - 输出 `子类的静态代码块`

  - 然后执行 `Father` 类的构造方法：

    ```java
    public Father() {
        System.out.println("我是父类");
    }
    ```

    - 输出 `我是父类`

  - 然后执行 `Son` 类的构造方法：

    ```java
    public Son() {
        System.out.println("我是子类");
    }
    ```

    - 输出 `我是子类`

- 最后回到 `InitializationDemo` 类的 `static` 部分，输出 `主类的静态代码块`

- 然后 `e` 终于被赋值 `5`

- 最后执行 `main` 方法，输出 `主类的静态方法`
</div>
</details>

我想，现在已经完全搞明白了类加载了。

## 垃圾回收

垃圾回收（Garbage Collection）是 Java 虚拟机的一个重要组成部分，它的作用是在程序运行时，自动回收不再使用的内存。

### 垃圾回收算法

#### 引用计数算法

引用计数算法（Reference Counting）是一种最基本的垃圾回收算法，它的原理是通过引用计数来判断对象是否存活。当对象被引用时，引用计数加 1；当对象被取消引用时，引用计数减 1。当引用计数为 0 时，说明对象不再被引用，可以被回收。

引用计数算法的优点是实现简单，缺点是无法解决循环引用的问题。

#### 标记-清除算法

标记-清除算法（Mark-and-Sweep）是一种最基本的垃圾回收算法，它分为两个阶段：

- 从一组根对象开始，递归地遍历所有的引用，标记所有的存活对象
- 遍历所有的对象，清除所有未标记的对象

标记-清除算法的优点是足够简单，缺点是会产生内存碎片。

这里的根对象是指一组对象，它们是程序的入口，可以直接或间接地引用到所有的对象。它们包括了：

- System Class，如 `java.util.*`
- JNI Local，即 native 方法中的局部变量
- JNI Global，即 native 方法中的全局变量
- Thread Block，即当前活跃线程引用的对象
- Thread，已经 `start` 但没有 `stop` 的线程
- Busy Monitor，即正在等待锁或者正在使用锁的线程
- Java Local，即仍然在线程栈中的对象
- Native Stack，例如用于文件或网络的方法或者反射
- Finalizable，即 `finalize` 方法还没有执行的对象
- Unfinalized，即有 `finalize` 方法但还没有执行的对象
- Unreachable，即不可达的对象，但被 MAT 标记为根
- Java Stack Frame，即 Java 栈帧中的对象
- Unknown，其它未知的对象

#### 复制算法

复制算法（Copying）是一种将内存分为两块的垃圾回收算法，分别为 `From` 和 `To`，正常只使用 `From` 块。它的垃圾回收过程分为以下几步：

- 从一组根对象开始，递归地遍历所有的引用，标记所有的存活对象
- 将存活的对象复制到 `To` 内存块
- 然后清理 `From` 内存块的所有对象
- 清除完毕后，将 `From` 和 `To` 互换

复制算法的优点是不会产生内存碎片，缺点是空间浪费了一半。

#### 标记-压缩算法

标记-压缩算法（Mark-and-Compact）

- 从一组根对象开始，递归地遍历所有的引用，标记所有的存活对象
- 将存活的对象压缩到内存的一端
- 清理另一端的剩余内存

标记-压缩算法的优点是不会产生内存碎片，缺点是需要扫描内存多次。

### 垃圾回收器

HotSpot VM 的内存被划分为几个区域：

- 新生代（Young Generation）：
  - Eden 区（约 80%）
  - From 区（约 10%）
  - To 区（约 10%）
- 老年代（Old Generation）
- 永久代（Permanent Generation）/ 元空间（Metaspace）

所有的对象都是在新生代的 Eden 区创建的，然后经过几次垃圾回收后，存活的对象会被移动到 From 区或 To 区，最后会被移动到老年代。

JVM 在不同的区域使用不同的垃圾回收器，下面我们来看一下这些垃圾回收器。

#### 串行收集器

串行收集器（Serial Collector）是一种单线程的垃圾回收器

- 新生代串行收集器使用的是复制算法，当垃圾回收时，其它所有的线程都会挂起，直到垃圾回收完成
- 老年代串行收集器使用的是标记-压缩算法，同样会触发 Stop-The-World

串行收集器适合用于并发能力较弱的机器上。

#### 并行收集器

并行收集器（Parallel Collector）是一种多线程的垃圾回收器

- 新生代 ParNew 收集器使用的是复制算法，它同样会触发 Stop-The-World，但由于使用了多线程，因此停顿的时间会更短
- 新生代 ParallelGC 收集器与 ParNew 收集器几乎相同，唯一的区别是它拥有自适应的调节策略，它可以设置最大停顿时间和最大吞吐量（即程序运行时间与垃圾回收时间的比值）
- 老年代 ParallelOldGC 收集器使用的是标记-压缩算法，同样会触发 Stop-The-World，但由于使用了多线程，因此停顿的时间会更短

并行收集器适合用于多核 CPU 的机器上，而在单核 CPU 的机器上反而会因为线程切换而降低性能。

#### CMS 收集器

CMS 收集器（Concurrent Mark-Sweep Collector）是一种并发的垃圾回收器。它在工作时分为以下几个阶段：

- 初始标记阶段（Initial Mark）：标记所有的根对象
- 并发标记阶段（Concurrent Mark）：并发地标记所有的存活对象
- 预清理阶段（Concurrent Preclean）：并发地清理所有的未标记对象
- 重新标记阶段（Remark）：重新标记所有的存活对象
- 并发清除阶段（Concurrent Sweep）：并发地清除所有的未标记对象
- 并发重置阶段（Concurrent Reset）：重置 CMS 收集器的内部状态

其中，只有初始标记阶段和重新标记阶段会触发 Stop-The-World，其它阶段都是并发的。

我们可以设置 CMS 不进行预清理，也可以让其在垃圾回收结束后整理内存碎片。

CMS 收集器适合用于对停顿时间要求较高的应用程序。

#### G1 收集器

G1 收集器（Garbage-First Collector）是一种面向服务端的垃圾回收器。它的特点是年轻代、老年代和元数据都可以不是连续的，而是由多个小块组成的。每个小块的大小可以设置为 1/2/4/8/16/31 MB。
